twitter.common.lang-0.3.10-py2.7-nspkg.pth
twitter/common/lang/__init__.py
twitter/common/lang/lockable.py
twitter.common.lang-0.3.10.dist-info/DESCRIPTION.rst
twitter.common.lang-0.3.10.dist-info/METADATA
twitter.common.lang-0.3.10.dist-info/RECORD
twitter.common.lang-0.3.10.dist-info/WHEEL
twitter.common.lang-0.3.10.dist-info/metadata.json
twitter.common.lang-0.3.10.dist-info/namespace_packages.txt
twitter.common.lang-0.3.10.dist-info/top_level.txt
twitter.common.lang-0.3.10.dist-info/zip-safe
